AUTHORS.rst
CONTRIBUTING.rst
HISTORY.rst
LICENSE
MANIFEST.in
README.rst
setup.cfg
setup.py
docs/Makefile
docs/authors.rst
docs/conf.py
docs/contributing.rst
docs/history.rst
docs/index.rst
docs/installation.rst
docs/make.bat
docs/readme.rst
docs/usage.rst
spip/__init__.py
spip/cli.py
spip/install.py
spip/packages.yml
spip.egg-info/PKG-INFO
spip.egg-info/SOURCES.txt
spip.egg-info/dependency_links.txt
spip.egg-info/entry_points.txt
spip.egg-info/not-zip-safe
spip.egg-info/requires.txt
spip.egg-info/top_level.txt
tests/test_av.py
tests/test_pillow.py