Metadata-Version: 1.1
Name: spip
Version: 0.3.2
Summary: pip <3 dnf/apt-get
Home-page: https://github.com/florianludwig/spip
Author: Florian Ludwig
Author-email: f.ludwig@greyrook.com
License: Apache Software License 2.0
Keywords: spip
Platform: UNKNOWN
Classifier: Development Status :: 2 - Pre-Alpha
Classifier: Intended Audience :: Developers
Classifier: License :: OSI Approved :: Apache Software License
Classifier: Natural Language :: English
Classifier: Programming Language :: Python :: 2
Classifier: Programming Language :: Python :: 2.6
Classifier: Programming Language :: Python :: 2.7
Classifier: Programming Language :: Python :: 3
Classifier: Programming Language :: Python :: 3.3
Classifier: Programming Language :: Python :: 3.4
Classifier: Programming Language :: Python :: 3.5
